odoo/addons/survey_xlsx/README.rst
odoo/addons/survey_xlsx/__init__.py
odoo/addons/survey_xlsx/__manifest__.py
odoo/addons/survey_xlsx/i18n/it.po
odoo/addons/survey_xlsx/i18n/survey_xlsx.pot
odoo/addons/survey_xlsx/models/__init__.py
odoo/addons/survey_xlsx/models/survey_user_input_line.py
odoo/addons/survey_xlsx/readme/CONTRIBUTORS.rst
odoo/addons/survey_xlsx/readme/DESCRIPTION.rst
odoo/addons/survey_xlsx/report/__init__.py
odoo/addons/survey_xlsx/report/report_survey_xlsx.py
odoo/addons/survey_xlsx/report/report_survey_xlsx.xml
odoo/addons/survey_xlsx/static/description/icon.png
odoo/addons/survey_xlsx/static/description/index.html
odoo/addons/survey_xlsx/tests/__init__.py
odoo/addons/survey_xlsx/tests/test_report.py
odoo13_addon_survey_xlsx-13.0.1.0.1.dev6.dist-info/METADATA
odoo13_addon_survey_xlsx-13.0.1.0.1.dev6.dist-info/WHEEL
odoo13_addon_survey_xlsx-13.0.1.0.1.dev6.dist-info/top_level.txt
odoo13_addon_survey_xlsx-13.0.1.0.1.dev6.dist-info/RECORD
